<?xml version="1.0" encoding="UTF-8"?>
<DocSetNodes version="1.0">
    <TOC>
        <Node type="folder">
            <Name>Bit6UI-SDK-for-iOS</Name>
            <Path>index.html</Path>
			<Subnodes>
                
				
				<Node type="folder">
					<Name>Classes</Name>
					<Path>index.html</Path>
					<Subnodes>
						<NodeRef refid="1"/>
						<NodeRef refid="2"/>
						<NodeRef refid="3"/>
						<NodeRef refid="4"/>
						<NodeRef refid="5"/>
						<NodeRef refid="6"/>
						<NodeRef refid="7"/>
						<NodeRef refid="8"/>
						<NodeRef refid="9"/>
						<NodeRef refid="10"/>
						<NodeRef refid="11"/>
						<NodeRef refid="12"/>
						<NodeRef refid="13"/>
						<NodeRef refid="14"/>
						<NodeRef refid="15"/>
						<NodeRef refid="16"/>
						<NodeRef refid="17"/>
						
					</Subnodes>
				</Node>
				
				
                
				<Node>
					<Name>Protocols</Name>
					<Path>index.html</Path>
					<Subnodes>
						<NodeRef refid="18"/>
						<NodeRef refid="19"/>
						<NodeRef refid="20"/>
						<NodeRef refid="21"/>
						<NodeRef refid="22"/>
						<NodeRef refid="23"/>
						<NodeRef refid="24"/>
						
					</Subnodes>
				</Node>
				
                
			</Subnodes>
        </Node>
    </TOC>
	<Library>
		
		<Node id="1" type="file" documentType="reference">
            <Name>BXU</Name>
            <Path>Classes/BXU.html</Path>
            
                <Subnodes>
                <Node type="section">
                    <Path>Classes/BXU.html</Path>
                    <Name>Overview</Name>
                    <Anchor>overview</Anchor>
                </Node>
                <Node type="section">
                    <Path>Classes/BXU.html</Path>
                    <Name>Tasks</Name>
                    <Anchor>tasks</Anchor>
                </Node>
                
                
                <Node type="section">
                    <Path>Classes/BXU.html</Path>
                    <Name>Class Methods</Name>
                    <Anchor>class_methods</Anchor>
                </Node>
                
                
                <Node type="section">
                    <Path>Classes/BXU.html</Path>
                    <Name>Instance Methods</Name>
                    <Anchor>instance_methods</Anchor>
                </Node>
                
            </Subnodes>
            
        </Node>
		<Node id="2" type="file" documentType="reference">
            <Name>BXUAttachmentImageView</Name>
            <Path>Classes/BXUAttachmentImageView.html</Path>
            
                <Subnodes>
                <Node type="section">
                    <Path>Classes/BXUAttachmentImageView.html</Path>
                    <Name>Overview</Name>
                    <Anchor>overview</Anchor>
                </Node>
                <Node type="section">
                    <Path>Classes/BXUAttachmentImageView.html</Path>
                    <Name>Tasks</Name>
                    <Anchor>tasks</Anchor>
                </Node>
                
                <Node type="section">
                    <Path>Classes/BXUAttachmentImageView.html</Path>
                    <Name>Properties</Name>
                    <Anchor>properties</Anchor>
                </Node>
                
                
                
                <Node type="section">
                    <Path>Classes/BXUAttachmentImageView.html</Path>
                    <Name>Instance Methods</Name>
                    <Anchor>instance_methods</Anchor>
                </Node>
                
            </Subnodes>
            
        </Node>
		<Node id="3" type="file" documentType="reference">
            <Name>BXUCallViewController</Name>
            <Path>Classes/BXUCallViewController.html</Path>
            
        </Node>
		<Node id="4" type="file" documentType="reference">
            <Name>BXUContactAvatarImageView</Name>
            <Path>Classes/BXUContactAvatarImageView.html</Path>
            
                <Subnodes>
                <Node type="section">
                    <Path>Classes/BXUContactAvatarImageView.html</Path>
                    <Name>Overview</Name>
                    <Anchor>overview</Anchor>
                </Node>
                <Node type="section">
                    <Path>Classes/BXUContactAvatarImageView.html</Path>
                    <Name>Tasks</Name>
                    <Anchor>tasks</Anchor>
                </Node>
                
                <Node type="section">
                    <Path>Classes/BXUContactAvatarImageView.html</Path>
                    <Name>Properties</Name>
                    <Anchor>properties</Anchor>
                </Node>
                
                
                <Node type="section">
                    <Path>Classes/BXUContactAvatarImageView.html</Path>
                    <Name>Class Methods</Name>
                    <Anchor>class_methods</Anchor>
                </Node>
                
                
            </Subnodes>
            
        </Node>
		<Node id="5" type="file" documentType="reference">
            <Name>BXUContactNameLabel</Name>
            <Path>Classes/BXUContactNameLabel.html</Path>
            
                <Subnodes>
                <Node type="section">
                    <Path>Classes/BXUContactNameLabel.html</Path>
                    <Name>Overview</Name>
                    <Anchor>overview</Anchor>
                </Node>
                <Node type="section">
                    <Path>Classes/BXUContactNameLabel.html</Path>
                    <Name>Tasks</Name>
                    <Anchor>tasks</Anchor>
                </Node>
                
                <Node type="section">
                    <Path>Classes/BXUContactNameLabel.html</Path>
                    <Name>Properties</Name>
                    <Anchor>properties</Anchor>
                </Node>
                
                
                
            </Subnodes>
            
        </Node>
		<Node id="6" type="file" documentType="reference">
            <Name>BXUConversationAvatarView</Name>
            <Path>Classes/BXUConversationAvatarView.html</Path>
            
                <Subnodes>
                <Node type="section">
                    <Path>Classes/BXUConversationAvatarView.html</Path>
                    <Name>Overview</Name>
                    <Anchor>overview</Anchor>
                </Node>
                <Node type="section">
                    <Path>Classes/BXUConversationAvatarView.html</Path>
                    <Name>Tasks</Name>
                    <Anchor>tasks</Anchor>
                </Node>
                
                <Node type="section">
                    <Path>Classes/BXUConversationAvatarView.html</Path>
                    <Name>Properties</Name>
                    <Anchor>properties</Anchor>
                </Node>
                
                
                
            </Subnodes>
            
        </Node>
		<Node id="7" type="file" documentType="reference">
            <Name>BXUConversationTableViewCell</Name>
            <Path>Classes/BXUConversationTableViewCell.html</Path>
            
                <Subnodes>
                <Node type="section">
                    <Path>Classes/BXUConversationTableViewCell.html</Path>
                    <Name>Overview</Name>
                    <Anchor>overview</Anchor>
                </Node>
                <Node type="section">
                    <Path>Classes/BXUConversationTableViewCell.html</Path>
                    <Name>Tasks</Name>
                    <Anchor>tasks</Anchor>
                </Node>
                
                <Node type="section">
                    <Path>Classes/BXUConversationTableViewCell.html</Path>
                    <Name>Properties</Name>
                    <Anchor>properties</Anchor>
                </Node>
                
                
                
            </Subnodes>
            
        </Node>
		<Node id="8" type="file" documentType="reference">
            <Name>BXUConversationTableViewController</Name>
            <Path>Classes/BXUConversationTableViewController.html</Path>
            
                <Subnodes>
                <Node type="section">
                    <Path>Classes/BXUConversationTableViewController.html</Path>
                    <Name>Overview</Name>
                    <Anchor>overview</Anchor>
                </Node>
                <Node type="section">
                    <Path>Classes/BXUConversationTableViewController.html</Path>
                    <Name>Tasks</Name>
                    <Anchor>tasks</Anchor>
                </Node>
                
                
                
                <Node type="section">
                    <Path>Classes/BXUConversationTableViewController.html</Path>
                    <Name>Instance Methods</Name>
                    <Anchor>instance_methods</Anchor>
                </Node>
                
            </Subnodes>
            
        </Node>
		<Node id="9" type="file" documentType="reference">
            <Name>BXUConversationsTabBarItem</Name>
            <Path>Classes/BXUConversationsTabBarItem.html</Path>
            
        </Node>
		<Node id="10" type="file" documentType="reference">
            <Name>BXUImageViewController</Name>
            <Path>Classes/BXUImageViewController.html</Path>
            
                <Subnodes>
                <Node type="section">
                    <Path>Classes/BXUImageViewController.html</Path>
                    <Name>Overview</Name>
                    <Anchor>overview</Anchor>
                </Node>
                <Node type="section">
                    <Path>Classes/BXUImageViewController.html</Path>
                    <Name>Tasks</Name>
                    <Anchor>tasks</Anchor>
                </Node>
                
                <Node type="section">
                    <Path>Classes/BXUImageViewController.html</Path>
                    <Name>Properties</Name>
                    <Anchor>properties</Anchor>
                </Node>
                
                
                
                <Node type="section">
                    <Path>Classes/BXUImageViewController.html</Path>
                    <Name>Instance Methods</Name>
                    <Anchor>instance_methods</Anchor>
                </Node>
                
            </Subnodes>
            
        </Node>
		<Node id="11" type="file" documentType="reference">
            <Name>BXUIncomingCallPrompt</Name>
            <Path>Classes/BXUIncomingCallPrompt.html</Path>
            
                <Subnodes>
                <Node type="section">
                    <Path>Classes/BXUIncomingCallPrompt.html</Path>
                    <Name>Overview</Name>
                    <Anchor>overview</Anchor>
                </Node>
                <Node type="section">
                    <Path>Classes/BXUIncomingCallPrompt.html</Path>
                    <Name>Tasks</Name>
                    <Anchor>tasks</Anchor>
                </Node>
                
                
                <Node type="section">
                    <Path>Classes/BXUIncomingCallPrompt.html</Path>
                    <Name>Class Methods</Name>
                    <Anchor>class_methods</Anchor>
                </Node>
                
                
                <Node type="section">
                    <Path>Classes/BXUIncomingCallPrompt.html</Path>
                    <Name>Instance Methods</Name>
                    <Anchor>instance_methods</Anchor>
                </Node>
                
            </Subnodes>
            
        </Node>
		<Node id="12" type="file" documentType="reference">
            <Name>BXULocationViewController</Name>
            <Path>Classes/BXULocationViewController.html</Path>
            
                <Subnodes>
                <Node type="section">
                    <Path>Classes/BXULocationViewController.html</Path>
                    <Name>Overview</Name>
                    <Anchor>overview</Anchor>
                </Node>
                <Node type="section">
                    <Path>Classes/BXULocationViewController.html</Path>
                    <Name>Tasks</Name>
                    <Anchor>tasks</Anchor>
                </Node>
                
                <Node type="section">
                    <Path>Classes/BXULocationViewController.html</Path>
                    <Name>Properties</Name>
                    <Anchor>properties</Anchor>
                </Node>
                
                
                
            </Subnodes>
            
        </Node>
		<Node id="13" type="file" documentType="reference">
            <Name>BXUMessageTableViewCell</Name>
            <Path>Classes/BXUMessageTableViewCell.html</Path>
            
                <Subnodes>
                <Node type="section">
                    <Path>Classes/BXUMessageTableViewCell.html</Path>
                    <Name>Overview</Name>
                    <Anchor>overview</Anchor>
                </Node>
                <Node type="section">
                    <Path>Classes/BXUMessageTableViewCell.html</Path>
                    <Name>Tasks</Name>
                    <Anchor>tasks</Anchor>
                </Node>
                
                <Node type="section">
                    <Path>Classes/BXUMessageTableViewCell.html</Path>
                    <Name>Properties</Name>
                    <Anchor>properties</Anchor>
                </Node>
                
                
                
            </Subnodes>
            
        </Node>
		<Node id="14" type="file" documentType="reference">
            <Name>BXUMessageTableViewController</Name>
            <Path>Classes/BXUMessageTableViewController.html</Path>
            
                <Subnodes>
                <Node type="section">
                    <Path>Classes/BXUMessageTableViewController.html</Path>
                    <Name>Overview</Name>
                    <Anchor>overview</Anchor>
                </Node>
                <Node type="section">
                    <Path>Classes/BXUMessageTableViewController.html</Path>
                    <Name>Tasks</Name>
                    <Anchor>tasks</Anchor>
                </Node>
                
                <Node type="section">
                    <Path>Classes/BXUMessageTableViewController.html</Path>
                    <Name>Properties</Name>
                    <Anchor>properties</Anchor>
                </Node>
                
                
                
                <Node type="section">
                    <Path>Classes/BXUMessageTableViewController.html</Path>
                    <Name>Instance Methods</Name>
                    <Anchor>instance_methods</Anchor>
                </Node>
                
            </Subnodes>
            
        </Node>
		<Node id="15" type="file" documentType="reference">
            <Name>BXUProgressWindow</Name>
            <Path>Classes/BXUProgressWindow.html</Path>
            
                <Subnodes>
                <Node type="section">
                    <Path>Classes/BXUProgressWindow.html</Path>
                    <Name>Overview</Name>
                    <Anchor>overview</Anchor>
                </Node>
                <Node type="section">
                    <Path>Classes/BXUProgressWindow.html</Path>
                    <Name>Tasks</Name>
                    <Anchor>tasks</Anchor>
                </Node>
                
                
                <Node type="section">
                    <Path>Classes/BXUProgressWindow.html</Path>
                    <Name>Class Methods</Name>
                    <Anchor>class_methods</Anchor>
                </Node>
                
                
            </Subnodes>
            
        </Node>
		<Node id="16" type="file" documentType="reference">
            <Name>BXUTypingLabel</Name>
            <Path>Classes/BXUTypingLabel.html</Path>
            
                <Subnodes>
                <Node type="section">
                    <Path>Classes/BXUTypingLabel.html</Path>
                    <Name>Overview</Name>
                    <Anchor>overview</Anchor>
                </Node>
                <Node type="section">
                    <Path>Classes/BXUTypingLabel.html</Path>
                    <Name>Tasks</Name>
                    <Anchor>tasks</Anchor>
                </Node>
                
                <Node type="section">
                    <Path>Classes/BXUTypingLabel.html</Path>
                    <Name>Properties</Name>
                    <Anchor>properties</Anchor>
                </Node>
                
                
                
            </Subnodes>
            
        </Node>
		<Node id="17" type="file" documentType="reference">
            <Name>BXUWebSocketStatusLabel</Name>
            <Path>Classes/BXUWebSocketStatusLabel.html</Path>
            
                <Subnodes>
                <Node type="section">
                    <Path>Classes/BXUWebSocketStatusLabel.html</Path>
                    <Name>Overview</Name>
                    <Anchor>overview</Anchor>
                </Node>
                <Node type="section">
                    <Path>Classes/BXUWebSocketStatusLabel.html</Path>
                    <Name>Tasks</Name>
                    <Anchor>tasks</Anchor>
                </Node>
                
                <Node type="section">
                    <Path>Classes/BXUWebSocketStatusLabel.html</Path>
                    <Name>Properties</Name>
                    <Anchor>properties</Anchor>
                </Node>
                
                
                
            </Subnodes>
            
        </Node>
		
		
        <Node id="18" type="file" documentType="reference">
            <Name>BXUAttachmentImageViewDelegate</Name>
            <Path>Protocols/BXUAttachmentImageViewDelegate.html</Path>
            
                <Subnodes>
                <Node type="section">
                    <Path>Protocols/BXUAttachmentImageViewDelegate.html</Path>
                    <Name>Overview</Name>
                    <Anchor>overview</Anchor>
                </Node>
                <Node type="section">
                    <Path>Protocols/BXUAttachmentImageViewDelegate.html</Path>
                    <Name>Tasks</Name>
                    <Anchor>tasks</Anchor>
                </Node>
                
                
                
                <Node type="section">
                    <Path>Protocols/BXUAttachmentImageViewDelegate.html</Path>
                    <Name>Instance Methods</Name>
                    <Anchor>instance_methods</Anchor>
                </Node>
                
            </Subnodes>
            
        </Node>
		<Node id="19" type="file" documentType="reference">
            <Name>BXUContact</Name>
            <Path>Protocols/BXUContact.html</Path>
            
                <Subnodes>
                <Node type="section">
                    <Path>Protocols/BXUContact.html</Path>
                    <Name>Overview</Name>
                    <Anchor>overview</Anchor>
                </Node>
                <Node type="section">
                    <Path>Protocols/BXUContact.html</Path>
                    <Name>Tasks</Name>
                    <Anchor>tasks</Anchor>
                </Node>
                
                
                
                <Node type="section">
                    <Path>Protocols/BXUContact.html</Path>
                    <Name>Instance Methods</Name>
                    <Anchor>instance_methods</Anchor>
                </Node>
                
            </Subnodes>
            
        </Node>
		<Node id="20" type="file" documentType="reference">
            <Name>BXUContactSource</Name>
            <Path>Protocols/BXUContactSource.html</Path>
            
                <Subnodes>
                <Node type="section">
                    <Path>Protocols/BXUContactSource.html</Path>
                    <Name>Overview</Name>
                    <Anchor>overview</Anchor>
                </Node>
                <Node type="section">
                    <Path>Protocols/BXUContactSource.html</Path>
                    <Name>Tasks</Name>
                    <Anchor>tasks</Anchor>
                </Node>
                
                
                
                <Node type="section">
                    <Path>Protocols/BXUContactSource.html</Path>
                    <Name>Instance Methods</Name>
                    <Anchor>instance_methods</Anchor>
                </Node>
                
            </Subnodes>
            
        </Node>
		<Node id="21" type="file" documentType="reference">
            <Name>BXUImageViewControllerDelegate</Name>
            <Path>Protocols/BXUImageViewControllerDelegate.html</Path>
            
                <Subnodes>
                <Node type="section">
                    <Path>Protocols/BXUImageViewControllerDelegate.html</Path>
                    <Name>Overview</Name>
                    <Anchor>overview</Anchor>
                </Node>
                <Node type="section">
                    <Path>Protocols/BXUImageViewControllerDelegate.html</Path>
                    <Name>Tasks</Name>
                    <Anchor>tasks</Anchor>
                </Node>
                
                
                
                <Node type="section">
                    <Path>Protocols/BXUImageViewControllerDelegate.html</Path>
                    <Name>Instance Methods</Name>
                    <Anchor>instance_methods</Anchor>
                </Node>
                
            </Subnodes>
            
        </Node>
		<Node id="22" type="file" documentType="reference">
            <Name>BXULocationViewControllerDelegate</Name>
            <Path>Protocols/BXULocationViewControllerDelegate.html</Path>
            
                <Subnodes>
                <Node type="section">
                    <Path>Protocols/BXULocationViewControllerDelegate.html</Path>
                    <Name>Overview</Name>
                    <Anchor>overview</Anchor>
                </Node>
                <Node type="section">
                    <Path>Protocols/BXULocationViewControllerDelegate.html</Path>
                    <Name>Tasks</Name>
                    <Anchor>tasks</Anchor>
                </Node>
                
                
                
                <Node type="section">
                    <Path>Protocols/BXULocationViewControllerDelegate.html</Path>
                    <Name>Instance Methods</Name>
                    <Anchor>instance_methods</Anchor>
                </Node>
                
            </Subnodes>
            
        </Node>
		<Node id="23" type="file" documentType="reference">
            <Name>BXUTypingLabelDelegate</Name>
            <Path>Protocols/BXUTypingLabelDelegate.html</Path>
            
                <Subnodes>
                <Node type="section">
                    <Path>Protocols/BXUTypingLabelDelegate.html</Path>
                    <Name>Overview</Name>
                    <Anchor>overview</Anchor>
                </Node>
                <Node type="section">
                    <Path>Protocols/BXUTypingLabelDelegate.html</Path>
                    <Name>Tasks</Name>
                    <Anchor>tasks</Anchor>
                </Node>
                
                
                
                <Node type="section">
                    <Path>Protocols/BXUTypingLabelDelegate.html</Path>
                    <Name>Instance Methods</Name>
                    <Anchor>instance_methods</Anchor>
                </Node>
                
            </Subnodes>
            
        </Node>
		<Node id="24" type="file" documentType="reference">
            <Name>BXUWebSocketStatusLabelDelegate</Name>
            <Path>Protocols/BXUWebSocketStatusLabelDelegate.html</Path>
            
                <Subnodes>
                <Node type="section">
                    <Path>Protocols/BXUWebSocketStatusLabelDelegate.html</Path>
                    <Name>Overview</Name>
                    <Anchor>overview</Anchor>
                </Node>
                <Node type="section">
                    <Path>Protocols/BXUWebSocketStatusLabelDelegate.html</Path>
                    <Name>Tasks</Name>
                    <Anchor>tasks</Anchor>
                </Node>
                
                
                
                <Node type="section">
                    <Path>Protocols/BXUWebSocketStatusLabelDelegate.html</Path>
                    <Name>Instance Methods</Name>
                    <Anchor>instance_methods</Anchor>
                </Node>
                
            </Subnodes>
            
        </Node>
		
        
	</Library>
</DocSetNodes>